confjson/__init__.py
confjson-1.3.0.dist-info/LICENSE
confjson-1.3.0.dist-info/WHEEL
confjson-1.3.0.dist-info/METADATA
confjson-1.3.0.dist-info/RECORD
