Metadata-Version: 2.1
Name: confjson
Version: 1.3.0
Summary: A bafflingly simple, JSON-backend configuration manager for python programs.
Home-page: https://github.com/skunkfrukt/confjson
License: UNKNOWN
Author: Namida Aneskans
Author-email: namida@skunkfrukt.se
Requires-Python: >=3.6
Classifier: Intended Audience :: Developers
Classifier: Programming Language :: Python :: 3.6
Classifier: Programming Language :: Python :: 3.7
Classifier: License :: Public Domain
Classifier: Operating System :: OS Independent
